README.md
setup.py
sweet.mobile.egg-info/PKG-INFO
sweet.mobile.egg-info/SOURCES.txt
sweet.mobile.egg-info/dependency_links.txt
sweet.mobile.egg-info/requires.txt
sweet.mobile.egg-info/top_level.txt
sweet/modules/mobile/__init__.py
sweet/modules/mobile/app.py
sweet/modules/mobile/config.py
sweet/modules/mobile/locator.py
sweet/modules/mobile/window.py