Metadata-Version: 2.1
Name: sweet.mobile
Version: 0.0.4
Summary: Sweet's mobile autotest module
Home-page: https://github.com/Sweeterio/mobile
Author: tonglei
Author-email: tonglei@qq.com
License: UNKNOWN
Platform: UNKNOWN
Classifier: Programming Language :: Python :: 3.9
Classifier: License :: OSI Approved :: MIT License
Classifier: Operating System :: OS Independent
